dirsync/__init__.py
dirsync/options.py
dirsync/run.py
dirsync/syncer.py
dirsync/version.py
dirsync-2.2.6.dist-info/LICENSE.txt
dirsync-2.2.6.dist-info/METADATA
dirsync-2.2.6.dist-info/WHEEL
dirsync-2.2.6.dist-info/entry_points.txt
dirsync-2.2.6.dist-info/top_level.txt
dirsync-2.2.6.dist-info/RECORD
