Metadata-Version: 2.2
Name: dirsync
Version: 2.2.6
Summary: Advanced directory tree synchronisation tool
Home-page: https://github.com/tkhyn/dirsync/
Author: Thomas Khyn
Author-email: thomas@ksytek.com
Keywords: directory,folder,update,synchronisation
Classifier: Programming Language :: Python
Classifier: Programming Language :: Python :: 2
Classifier: Programming Language :: Python :: 3
Classifier: License :: OSI Approved :: MIT License
Classifier: Operating System :: OS Independent
Classifier: Development Status :: 5 - Production/Stable
Classifier: Intended Audience :: Developers
Classifier: Intended Audience :: End Users/Desktop
Classifier: Environment :: Console
Classifier: Topic :: Utilities
Classifier: Topic :: Desktop Environment
Classifier: Topic :: System :: Archiving :: Backup
Classifier: Topic :: System :: Archiving :: Mirroring
License-File: LICENSE.txt
Dynamic: author
Dynamic: author-email
Dynamic: classifier
Dynamic: description
Dynamic: home-page
Dynamic: keywords
Dynamic: summary
